Metadata-Version: 1.1
Name: vire
Version: 0.2.0
Summary: Vim / Neovim installer and plugin manager
Home-page: https://github.com/genotrance/vire
Author: Ganesh Viswanathan
Author-email: dev@genotrance.com
License: UNKNOWN
Download-URL: https://github.com/genotrance/vire/archive/0.2.0.tar.gz
Project-URL: Bug Reports, https://github.com/genotrance/vire/issues
Project-URL: Source, https://github.com/genotrance/vire
Keywords: vim vimrc neovim plugin
Platform: UNKNOWN
Classifier: Development Status :: 4 - Beta
Classifier: Intended Audience :: Developers
Classifier: Intended Audience :: End Users/Desktop
Classifier: License :: OSI Approved :: MIT License
Classifier: Natural Language :: English
Classifier: Programming Language :: Python :: 2.7
Classifier: Programming Language :: Python :: 3.4
Classifier: Programming Language :: Python :: 3.5
Classifier: Programming Language :: Python :: 3.6
Classifier: Programming Language :: Python :: 3.7
Classifier: Topic :: Utilities
